{
    "title": {
        "en": "Current price"
    },
    "desc": {
        "en": "Current electricity price"
    },
    "tokens": [
        {
            "name": "current_hour_price",
            "type": "number",
            "title": {
                "en": "PLN/kWh"
            },
            "example": 0.505
        }
    ],
    "type": "number",
    "min": -5,
    "max": 5,
    "decimals": 4,
    "units": {
        "en": "PLN/kWh"
    },
    "getable": true,
    "setable": false,
    "insights": true,
    "uiComponent": "sensor",
    "icon": "/assets/icon.svg",
    "color": {
        "type": "continuous",
        "value": {
            "minimum": -1,
            "maximum": 3,
            "stops": [
                {
                    "value": -1,
                    "color": "#0cce6b"
                },
                {
                    "value": 0,
                    "color": "#43c3ff" 
                },
                {
                    "value": 1,
                    "color": "#ffd00a"
                },
                {
                    "value": 2,
                    "color": "#ff9600"
                },
                {
                    "value": 3,
                    "color": "#ff2a00"
                }
            ]
        }
    }
}
